{
  "mangas": [
    {
      "id": 1,
      "name": "One Piece",
      "coverUrl": "https://upload.wikimedia.org/wikipedia/en/2/29/OnePieceVolume1Cover.jpg",
      "description": "Monkey D. Luffy part en mer pour devenir le Roi des Pirates.",
      "author": "Eiichiro Oda",
      "publicationYear": 1997,
      "theme": "Aventure",
      "type": "Shonen",
      "genre": "Action, Aventure, Comédie",
      "telegramLink": "https://t.me/onepiece_officiel"
    },
    {
      "id": 2,
      "name": "Naruto",
      "coverUrl": "https://upload.wikimedia.org/wikipedia/en/9/94/NarutoCoverTankobon1.jpg",
      "description": "L’histoire de Naruto Uzumaki, un jeune ninja qui rêve de devenir Hokage.",
      "author": "Masashi Kishimoto",
      "publicationYear": 1999,
      "theme": "Ninja",
      "type": "Shonen",
      "genre": "Action, Aventure, Fantastique",
      "telegramLink": "https://t.me/naruto_manga"
    },
    {
      "id": 3,
      "name": "Attack on Titan",
      "coverUrl": "https://upload.wikimedia.org/wikipedia/en/7/77/Shingeki_no_Kyojin_manga_volume_1.jpg",
      "description": "L’humanité lutte pour survivre contre les Titans dans un monde post-apocalyptique.",
      "author": "Hajime Isayama",
      "publicationYear": 2009,
      "theme": "Survie",
      "type": "Shonen",
      "genre": "Action, Drame, Surnaturel",
      "telegramLink": "https://t.me/aot_fans"
    }
  ]
}
